{"Central Africa Time":{"SID":"CAT","UTC":[2]},"Central European Time":{"SID":"CET","UTC":[1]},"Cape Verde Time":{"SID":"CVT","UTC":[-1]},"Eastern Africa Time":{"SID":"EAT","UTC":[3]},"Eastern European Time":{"SID":"EET","UTC":[2]},"Greenwich Mean Time":{"SID":"GMT","UTC":[0]},"Mauritius Time":{"SID":"MUT","UTC":[4]},"Reunion Time":{"SID":"RET","UTC":[4]},"South Africa Standard Time":{"SID":"SAST","UTC":[2]},"Seychelles Time":{"SID":"SCT","UTC":[4]},"West Africa Summer Time":{"SID":"WAST","UTC":[2]},"West Africa Time":{"SID":"WAT","UTC":[1]},"Western European Summer Time":{"SID":"WEST","UTC":[1]},"Western European Time":{"SID":"WET","UTC":[0]},"Western Sahara Summer Time":{"SID":"WST","UTC":[1]},"Western Sahara Standard Time":{"SID":"WT","UTC":[0]}}